awspolicy/__init__.py
awspolicy/aws_policy_modules.py
awspolicy-0.0.3.1.dist-info/METADATA
awspolicy-0.0.3.1.dist-info/RECORD
awspolicy-0.0.3.1.dist-info/WHEEL
awspolicy-0.0.3.1.dist-info/top_level.txt
