Metadata-Version: 2.1
Name: awspolicy
Version: 0.0.3.1
Summary: A package that helps modifying AWS policies as an object
Home-page: https://github.com/totoleon/AwsPolicy
Author: Hailong Li
Author-email: hailong.leon@gmail.com
License: UNKNOWN
Platform: UNKNOWN
Classifier: Programming Language :: Python :: 3
Classifier: License :: OSI Approved :: MIT License
Classifier: Operating System :: OS Independent
